LICENSE.txt
setup.py
code/__init__.py
pyme73.egg-info/PKG-INFO
pyme73.egg-info/SOURCES.txt
pyme73.egg-info/dependency_links.txt
pyme73.egg-info/top_level.txt