Metadata-Version: 2.1
Name: pyme73
Version: 0.1
Summary: library in python language
Author: Mo7amed El3omda
Classifier: Programming Language :: Python :: 3
Classifier: Operating System :: OS Independent
Classifier: License :: OSI Approved :: MIT License
License-File: LICENSE.txt
